lfclib.cpython-313-darwin.so
mulfc-0.0.4.dist-info/RECORD
mulfc-0.0.4.dist-info/WHEEL
mulfc-0.0.4.dist-info/top_level.txt
mulfc-0.0.4.dist-info/METADATA
mulfc/__init__.py
mulfc/lfclib.c
mulfc/LFC.py
