Metadata-Version: 2.1
Name: mulfc
Version: 0.0.4
Summary: Local Field Components (or lighting fast calculator) at muon sites for the muesr package.
Home-page: https://github.com/bonfus/muLFC
Author: Pietro Bonfa
Author-email: Pietro Bonfa <bonfus@gmail.com>, Pietro Bonfa <pietro.bonfa@unipr.it>
License: GPLv3
Project-URL: Homepage, https://github.com/bonfus/muLFC
Classifier: License :: OSI Approved :: GNU General Public License v3 or later (GPLv3+)
Classifier: Programming Language :: Python
Classifier: Programming Language :: Python :: 3
Classifier: Topic :: Scientific/Engineering :: Physics
Requires-Python: >=3.7
Requires-Dist: numpy >=1.8
